{
  "type_id": 4054,
  "name": "女式'执行官'外套",
  "description": "设计者：拉奈会所\n\n在当今险恶的星际政治环境中，时刻保持一副威风的外表至关重要。莱索烷和蛛丝面料，“执行官”立领外套，彰显领导范式。全新设计，线条简洁，顺滑贴身，塑造不折不扣的气质。完美收腰，搭配丝质细节，您的飒爽英姿，为万众瞩目。",
  "volume": 0.1,
  "repackaged_volume": null,
  "capacity": null,
  "mass": 0.5,
  "category_name": "服饰",
  "group_name": "外套",
  "attributes": [
    {
      "attribute_name": "gender",
      "value": 3.0,
      "categoryID": 7,
      "display_name": "性别",
      "unit_name": "1=男性 2=中性 3=女性"
    }
  ],
  "traits": []
}